terraform_runner/__init__.py
terraform_runner/terraform_runner.py
terraform_runner-1.0.2.dist-info/METADATA
terraform_runner-1.0.2.dist-info/WHEEL
terraform_runner-1.0.2.dist-info/top_level.txt
terraform_runner-1.0.2.dist-info/RECORD
